LAB_3/CO_Lab3_給學生用/MEMORY.v
`timescale 1ns/1ps

module MEMORY(
	clk,
	rst,
	XM_MemtoReg,
	XM_RegWrite,
	XM_MemRead,
	XM_MemWrite,
	ALUout,
	XM_RD,
	XM_MD,

	MW_MemtoReg,
	MW_RegWrite,
	MW_ALUout,
	MDR,
	MW_RD
);
input clk, rst, XM_MemtoReg, XM_RegWrite, XM_MemRead, XM_MemWrite;

input [31:0] ALUout;
input [4:0] XM_RD;
input [31:0] XM_MD;


output reg MW_MemtoReg, MW_RegWrite;
output reg [31:0]	MW_ALUout, MDR;
output reg [4:0]	MW_RD;

//data memory
reg [31:0] DM [0:127];

always @(posedge clk)
	if(XM_MemWrite)
		DM[ALUout[6:0]] <= XM_MD;

always @(posedge clk or posedge rst)
	if (rst) begin
		MW_MemtoReg 		<= 1'b0;
		MW_RegWrite 		<= 1'b0;
		MDR					<= 32'b0;
		MW_ALUout			<= 32'b0;
		MW_RD				<= 5'b0;
	end
	else begin
		MW_MemtoReg 		<= XM_MemtoReg;
		MW_RegWrite 		<= XM_RegWrite;
		MDR					<= (XM_MemRead)?DM[ALUout[6:0]]:MDR;
		MW_ALUout			<= ALUout;
		MW_RD 				<= XM_RD;
	end

endmodule

LAB_3/CO_Lab3_給學生用/EXECUTION.v
`timescale 1ns/1ps

module EXECUTION(
	clk,
	rst,
	DX_MemtoReg,
	DX_RegWrite,
	DX_MemRead,
	DX_MemWrite,
	DX_branch,
	ALUctr,
	NPC,
	A,
	B,
	imm,
	DX_RD,
	DX_MD,
	
	JT,
	DX_PC,
	DX_jump,

	XM_MemtoReg,
	XM_RegWrite,
	XM_MemRead,
	XM_MemWrite,
	XM_branch,
	ALUout,
	XM_RD,
	XM_MD,
	XM_BT
);

input clk, rst, DX_MemtoReg, DX_RegWrite, DX_MemRead, DX_MemWrite, DX_branch, DX_jump;
input [2:0] ALUctr;
input [31:0]JT, DX_PC, NPC, A, B;
input [15:0]imm;
input [4:0] DX_RD;
input [31:0] DX_MD;

output reg XM_MemtoReg, XM_RegWrite, XM_MemRead, XM_MemWrite, XM_branch;
output reg [31:0]ALUout, XM_BT;
output reg [4:0] XM_RD;
output reg [31:0] XM_MD;

//set pipeline register
always @(posedge clk or posedge rst)
begin
	if(rst) begin //初始化
		XM_MemtoReg	<= 1'b0;
		XM_RegWrite	<= 1'b0;
		XM_MemRead 	<= 1'b0;
		XM_MemWrite	<= 1'b0;
		XM_RD 	   	<= 5'b0;
		XM_MD 	   	<= 32'b0;
		XM_branch	<= 1'b0;
		XM_BT		<=32'b0;
	end else begin
		XM_MemtoReg	<= DX_MemtoReg;
		XM_RegWrite	<= DX_RegWrite;
		XM_MemRead 	<= DX_MemRead;
		XM_MemWrite	<= DX_MemWrite;
		XM_RD 	   	<= DX_RD;
		XM_MD 	   	<= DX_MD;
	    XM_branch<=((ALUctr==5) && (A == B) && (DX_branch))? 1'b1: ((ALUctr==6) && (A != B) && (DX_branch))?1'b1:1'b0;
		XM_BT<=NPC+{ { 15{imm[15]}}, imm, 2'b0};  //Branch Target = 當前的PC值 + 相對位址 (EX. beq指令)
		//beq指令在"execution"中所需要的設定其實大多都完成了，各位可以參閱上方兩行指令。但下方ALUout還是記得要給個值，例如：0
	end
end

always @(posedge clk or posedge rst)
begin
   if(rst) begin
   		ALUout <= 32'b0;
   end else begin
   		case(ALUctr)
			
		  	3'd0: //add / lw ...  //在ID階段時已經解碼出指令了，那該指令需要哪一種運算?
		     	ALUout <= A + B;
		  			 	
		endcase
   end
end


endmodule

LAB_3/CO_Lab3_給學生用/INSTRUCTION_DECODE.v
`timescale 1ns/1ps

module INSTRUCTION_DECODE(
	clk,
	rst,
	PC,
	IR,
	MW_MemtoReg,
	MW_RegWrite,
	MW_RD,
	MDR,
	MW_ALUout,

	MemtoReg,
	RegWrite,
	MemRead,
	MemWrite,
	branch,
	jump,
	ALUctr,
	JT,
	DX_PC,
	NPC,
	A,
	B,
	imm,
	RD,
	MD,
);

input clk, rst, MW_MemtoReg, MW_RegWrite;
input [31:0] IR, PC, MDR, MW_ALUout;
input [4:0]  MW_RD;

output reg MemtoReg, RegWrite, MemRead, MemWrite, branch, jump;
output reg [2:0] ALUctr;
output reg [31:0]JT, DX_PC, NPC, A, B;
output reg [15:0]imm;
output reg [4:0] RD;
output reg [31:0] MD;

//register file
reg [31:0] REG [0:31];

always @(posedge clk or posedge rst)
	if(rst) begin
		A 	<=32'b0;
	end
	else if(MW_RegWrite)
		REG[MW_RD] <= (MW_MemtoReg)? MDR : MW_ALUout;

always @(posedge clk or posedge rst)
begin
	if(rst) begin //初始化
		A 	<=32'b0;		
		MD 	<=32'b0;
		imm <=16'b0;
	    DX_PC<=32'b0;
		NPC	<=32'b0;
		jump 	<=1'b0;
		JT 	<=32'b0;
	end else begin
		A 	<=REG[IR[25:21]];
		MD 	<=REG[IR[20:16]];
		imm <=IR[15:0];
	    DX_PC<=PC;
		NPC	<=PC;
		jump<=(IR[31:26]==6'd2)?1'b1:1'b0;
		JT	<={PC[31:28], IR[26:0], 2'b0};
		
	end
end

always @(posedge clk or posedge rst)
begin
   if(rst) begin
   	B 		<= 32'b0;
		MemtoReg<= 1'b0;
		RegWrite<= 1'b0;
		MemRead <= 1'b0;
		MemWrite<= 1'b0;
		branch  <= 1'b0;
		ALUctr	<= 3'b0;
		RD 	<=5'b0;
		
   end else begin
   		case( IR[31:26] )
		6'd0:
			begin  // R-type
				B 		<= REG[IR[20:16]];
				RD 	<=IR[15:11];
				MemtoReg<= 1'b0;
				RegWrite<= 1'b1;
				MemRead <= 1'b0;
				MemWrite<= 1'b0;
				branch  <= 1'b0;
			    case(IR[5:0])
			    	//funct
				    6'd32://add
				        ALUctr <= 3'd0;
					//sub
					
					//and
					
					//or
					
					//slt
					    
		    	endcase
			end
		6'd35:  begin// lw   //寫之前先看該指令格式及訊號線哪些該打開哪些該關閉，input A在上述已經設定好了，那還需要設定什麼? for example:
				//B 		<= { { 16{IR[15]} } , IR[15:0] };
			    //RD 	<=IR[20:16];
			    //MemtoReg<= 1'b1;
			    //RegWrite<= 1'b1;
			    //MemRead <= 1'b1;
			    //MemWrite<= 1'b0;
			    //branch  <= 1'b0;
			    //ALUctr  <= 3'd0;
			    
		 	end
		6'd43:  begin// sw  //其實做法都很雷同，確認好指令格式及訊號線即可
				
			    
		 	end
		6'd4:   begin // beq
				
			end
		6'd5:   begin // bne
			    
			end
		6'd2: begin  // j
			  
			end

			default: begin
				//$display("ERROR instruction!!");
			end
		endcase
   end
end

endmodule

LAB_3/CO_Lab3_給學生用/INSTRUCTION_FETCH.v
`timescale 1ns/1ps

module INSTRUCTION_FETCH(
	clk,
	rst,
	jump,
	branch,
	jump_addr,
	branch_addr,

	PC,
	IR
);

input clk, rst, jump, branch;
input [31:0] jump_addr, branch_addr;

output reg 	[31:0] PC;
output reg 	[31:0] IR;

reg [31:0] instruction [255:0];
//output instruction
always @(posedge clk or posedge rst)
begin
	if(rst)
		IR <= 32'd0;
	else
		IR <= instruction[PC[10:2]]; //(0, 4, 8, ...) => (0, 1, 2, ...)
end

// output program counter
always @(posedge clk or posedge rst)
begin
	if(rst)
		PC <= 32'd0;
	else
		PC <= (branch) ? branch_addr : ( (jump) ? jump_addr : (PC+4)) ;
end

endmodule

LAB_3/iverilog/bin/CPU.v
`timescale 1ns/1ps

`include "INSTRUCTION_FETCH.v"
`include "INSTRUCTION_DECODE.v"
`include "EXECUTION.v"
`include "MEMORY.v"

module CPU(
	clk,
	rst
);
input clk, rst;
/*============================== Wire  ==============================*/
wire [7:0] GCD_OUTPUT;
//wire LI0,LI1,LI2,LI3,LI4,LI5,LI6,LI7,MI0,MI1,MI2,MI3,MI4,MI5,MI6,MI7,RI0,RI1,RI2,RI3,RI4,RI5,RI6,RI7;

// INSTRUCTION_FETCH wires
wire [31:0] FD_PC;
wire [31:0] FD_IR;

// INSTRUCTION_DECODE wires
wire DX_MemtoReg, DX_RegWrite, DX_MemRead, DX_MemWrite, DX_jump, DX_branch;
wire [31:0] DX_JT, DX_PC, DX_NPC, A, B;
wire [15:0] imm;
wire [4:0] DX_RD;
wire [31:0] DX_MD;
wire [2:0] ALUctr;

// EXECUTION wires
wire XM_MemtoReg, XM_RegWrite, XM_MemRead, XM_MemWrite, XM_branch;
wire [31:0] XM_ALUout;
wire [31:0] XM_BT;
wire [4:0] XM_RD;
wire [31:0] XM_MD;

// DATA_MEMORY wires
wire MW_MemtoReg, MW_RegWrite;
wire [31:0] 	MDR, MW_ALUout;
wire [5-1:0]	MW_RD;
/*============================== INSTRUCTION_FETCH ==============================*/
INSTRUCTION_FETCH IF(
	.clk(clk),
	.rst(rst),
	.jump(DX_jump),
	.branch(XM_branch),
	.jump_addr(DX_JT),
	.branch_addr(XM_BT),

	.PC(FD_PC),
	.IR(FD_IR)
);

/*============================== INSTRUCTION_DECODE ==============================*/

INSTRUCTION_DECODE ID(
	.clk(clk),
	.rst(rst),
	.PC(FD_PC),
	.IR(FD_IR),
	.MW_MemtoReg(MW_MemtoReg),
	.MW_RegWrite(MW_RegWrite),
	.MW_RD(MW_RD),
	.MDR(MDR),
	.MW_ALUout(MW_ALUout),

	.MemtoReg(DX_MemtoReg),
	.RegWrite(DX_RegWrite),
	.MemRead(DX_MemRead),
	.MemWrite(DX_MemWrite),
	.branch(DX_branch),
	.jump(DX_jump),
	.ALUctr(ALUctr),
	.JT(DX_JT),
	.DX_PC(DX_PC),
	.NPC(DX_NPC),
	.A(A),
	.B(B),
	.imm(imm),
	.RD(DX_RD),
	.MD(DX_MD)	
);

/*==============================     EXECUTION  	==============================*/

EXECUTION EXE(
	.clk(clk),
	.rst(rst),
	.DX_MemtoReg(DX_MemtoReg),
	.DX_RegWrite(DX_RegWrite),
	.DX_MemRead(DX_MemRead),
	.DX_MemWrite(DX_MemWrite),
	.DX_branch(DX_branch),
	.ALUctr(ALUctr),
	.NPC(DX_NPC),
	.A(A),
	.B(B),
	.imm(imm),
	.DX_RD(DX_RD),
	.DX_MD(DX_MD),

	.XM_MemtoReg(XM_MemtoReg),
	.XM_RegWrite(XM_RegWrite),
	.XM_MemRead(XM_MemRead),
	.XM_MemWrite(XM_MemWrite),
	.XM_branch(XM_branch),
	.ALUout(XM_ALUout),
	.XM_RD(XM_RD),
	.XM_MD(XM_MD),
	.XM_BT(XM_BT)
);

/*==============================     DATA_MEMORY	==============================*/

MEMORY MEM(
	.clk(clk),
	.rst(rst),
	.XM_MemtoReg(XM_MemtoReg),
	.XM_RegWrite(XM_RegWrite),
	.XM_MemRead(XM_MemRead),
	.XM_MemWrite(XM_MemWrite),
	.ALUout(XM_ALUout),
	.XM_RD(XM_RD),
	.XM_MD(XM_MD),

	.MW_MemtoReg(MW_MemtoReg),
	.MW_RegWrite(MW_RegWrite),
	.MW_ALUout(MW_ALUout),
	.MDR(MDR),
	.MW_RD(MW_RD)
);



endmodule

LAB_3/CO_Lab3_給學生用/testbench.v
`define CYCLE_TIME 20
`define INSTRUCTION_NUMBERS 20
`timescale 1ns/1ps
`include "CPU.v"

module testbench;
reg Clk, Rst;
reg [31:0] cycles, i;

// Instruction DM initialilation
initial
begin
	/*=================================================     連加     =================================================*/
		cpu.IF.instruction[ 0] = 32'b000000_00001_00010_00011_00000_100000;	//add $3, $1, $2       $3 = 1 + 2 = 3
		cpu.IF.instruction[ 1] = 32'b000000_00000_00000_00000_00000_100000;	//NOP(add $0, $0, $0)
		cpu.IF.instruction[ 2] = 32'b000000_00000_00000_00000_00000_100000;	//NOP(add $0, $0, $0)
		cpu.IF.instruction[ 3] = 32'b000000_00000_00000_00000_00000_100000;	//NOP(add $0, $0, $0)	
		cpu.IF.PC = 0;
		
		
		
	
end

// Data Memory & Register Files initialilation
initial
begin
	cpu.MEM.DM[0] = 32'd9;
	cpu.MEM.DM[1] = 32'd3;
	for (i=2; i<128; i=i+1) cpu.MEM.DM[i] = 32'b0;
	
	cpu.ID.REG[0] = 32'd0;
	cpu.ID.REG[1] = 32'd1;
	cpu.ID.REG[2] = 32'd2;

	for (i=3; i<32; i=i+1) cpu.ID.REG[i] = 32'b0;
	
	


end

//clock cycle time is 20ns, inverse Clk value per 10ns
initial Clk = 1'b1;
always #(`CYCLE_TIME/2) Clk = ~Clk;

//Rst signal
initial begin
	cycles = 32'b0;
	Rst = 1'b1;
	#12 Rst = 1'b0;
end

CPU cpu(
	.clk(Clk),
	.rst(Rst)
);

//display all Register value and Data memory content
always @(posedge Clk) begin
	cycles <= cycles + 1;
	if (cycles == `INSTRUCTION_NUMBERS) $finish; // Finish when excute the 24-th instruction (End label).
	$display("PC: %d cycles: %d", cpu.FD_PC>>2 , cycles);
	$display("  R00-R07: %08x %08x %08x %08x %08x %08x %08x %08x", cpu.ID.REG[0], cpu.ID.REG[1], cpu.ID.REG[2], cpu.ID.REG[3],cpu.ID.REG[4], cpu.ID.REG[5], cpu.ID.REG[6], cpu.ID.REG[7]);
	$display("  R08-R15: %08x %08x %08x %08x %08x %08x %08x %08x", cpu.ID.REG[8], cpu.ID.REG[9], cpu.ID.REG[10], cpu.ID.REG[11],cpu.ID.REG[12], cpu.ID.REG[13], cpu.ID.REG[14], cpu.ID.REG[15]);
	$display("  R16-R23: %08x %08x %08x %08x %08x %08x %08x %08x", cpu.ID.REG[16], cpu.ID.REG[17], cpu.ID.REG[18], cpu.ID.REG[19],cpu.ID.REG[20], cpu.ID.REG[21], cpu.ID.REG[22], cpu.ID.REG[23]);
	$display("  R24-R31: %08x %08x %08x %08x %08x %08x %08x %08x", cpu.ID.REG[24], cpu.ID.REG[25], cpu.ID.REG[26], cpu.ID.REG[27],cpu.ID.REG[28], cpu.ID.REG[29], cpu.ID.REG[30], cpu.ID.REG[31]);
	$display("  0x00   : %08x %08x %08x %08x %08x %08x %08x %08x", cpu.MEM.DM[0],cpu.MEM.DM[1],cpu.MEM.DM[2],cpu.MEM.DM[3],cpu.MEM.DM[4],cpu.MEM.DM[5],cpu.MEM.DM[6],cpu.MEM.DM[7]);
	$display("  0x08   : %08x %08x %08x %08x %08x %08x %08x %08x", cpu.MEM.DM[8],cpu.MEM.DM[9],cpu.MEM.DM[10],cpu.MEM.DM[11],cpu.MEM.DM[12],cpu.MEM.DM[13],cpu.MEM.DM[14],cpu.MEM.DM[15]);
end

//generate wave file, it can use gtkwave to display
initial begin
	$dumpfile("cpu_hw.vcd");
	$dumpvars;
end
endmodule

LAB_3/CO_Lab3_給學生用/cpu_hw.vcd
$date
	Mon Nov 12 15:48:53 2018
$end
$version
	Icarus Verilog
$end
$timescale
	1ps
$end
$scope module testbench $end
$var reg 1 ! Clk $end
$var reg 1 " Rst $end
$var reg 32 # cycles [31:0] $end
$var reg 32 $ i [31:0] $end
$scope module cpu $end
$var wire 32 % A [31:0] $end
$var wire 3 & ALUctr [2:0] $end
$var wire 32 ' B [31:0] $end
$var wire 32 ( DX_JT [31:0] $end
$var wire 32 ) DX_MD [31:0] $end
$var wire 1 * DX_MemRead $end
$var wire 1 + DX_MemWrite $end
$var wire 1 , DX_MemtoReg $end
$var wire 32 - DX_NPC [31:0] $end
$var wire 32 . DX_PC [31:0] $end
$var wire 5 / DX_RD [4:0] $end
$var wire 1 0 DX_RegWrite $end
$var wire 1 1 DX_branch $end
$var wire 1 2 DX_jump $end
$var wire 32 3 FD_IR [31:0] $end
$var wire 32 4 FD_PC [31:0] $end
$var wire 32 5 MDR [31:0] $end
$var wire 32 6 MW_ALUout [31:0] $end
$var wire 1 7 MW_MemtoReg $end
$var wire 5 8 MW_RD [4:0] $end
$var wire 1 9 MW_RegWrite $end
$var wire 32 : XM_ALUout [31:0] $end
$var wire 32 ; XM_BT [31:0] $end
$var wire 32 < XM_MD [31:0] $end
$var wire 1 = XM_MemRead $end
$var wire 1 > XM_MemWrite $end
$var wire 1 ? XM_MemtoReg $end
$var wire 5 @ XM_RD [4:0] $end
$var wire 1 A XM_RegWrite $end
$var wire 1 B XM_branch $end
$var wire 1 C clk $end
$var wire 16 D imm [15:0] $end
$var wire 1 E rst $end
$scope module IF $end
$var wire 1 B branch $end
$var wire 32 F branch_addr [31:0] $end
$var wire 1 C clk $end
$var wire 1 2 jump $end
$var wire 32 G jump_addr [31:0] $end
$var wire 1 E rst $end
$var reg 32 H IR [31:0] $end
$var reg 32 I PC [31:0] $end
$upscope $end
$scope module ID $end
$var wire 32 J IR [31:0] $end
$var wire 32 K MDR [31:0] $end
$var wire 32 L MW_ALUout [31:0] $end
$var wire 1 7 MW_MemtoReg $end
$var wire 5 M MW_RD [4:0] $end
$var wire 1 9 MW_RegWrite $end
$var wire 32 N PC [31:0] $end
$var wire 1 C clk $end
$var wire 1 E rst $end
$var reg 32 O A [31:0] $end
$var reg 3 P ALUctr [2:0] $end
$var reg 32 Q B [31:0] $end
$var reg 32 R DX_PC [31:0] $end
$var reg 32 S JT [31:0] $end
$var reg 32 T MD [31:0] $end
$var reg 1 U MemRead $end
$var reg 1 V MemWrite $end
$var reg 1 W MemtoReg $end
$var reg 32 X NPC [31:0] $end
$var reg 5 Y RD [4:0] $end
$var reg 1 Z RegWrite $end
$var reg 1 [ branch $end
$var reg 16 \ imm [15:0] $end
$var reg 1 ] jump $end
$upscope $end
$scope module EXE $end
$var wire 32 ^ A [31:0] $end
$var wire 3 _ ALUctr [2:0] $end
$var wire 32 ` B [31:0] $end
$var wire 32 a DX_MD [31:0] $end
$var wire 1 * DX_MemRead $end
$var wire 1 + DX_MemWrite $end
$var wire 1 , DX_MemtoReg $end
$var wire 32 b DX_PC [31:0] $end
$var wire 5 c DX_RD [4:0] $end
$var wire 1 0 DX_RegWrite $end
$var wire 1 1 DX_branch $end
$var wire 1 d DX_jump $end
$var wire 32 e JT [31:0] $end
$var wire 32 f NPC [31:0] $end
$var wire 1 C clk $end
$var wire 16 g imm [15:0] $end
$var wire 1 E rst $end
$var reg 32 h ALUout [31:0] $end
$var reg 32 i XM_BT [31:0] $end
$var reg 32 j XM_MD [31:0] $end
$var reg 1 k XM_MemRead $end
$var reg 1 l XM_MemWrite $end
$var reg 1 m XM_MemtoReg $end
$var reg 5 n XM_RD [4:0] $end
$var reg 1 o XM_RegWrite $end
$var reg 1 p XM_branch $end
$upscope $end
$scope module MEM $end
$var wire 32 q ALUout [31:0] $end
$var wire 32 r XM_MD [31:0] $end
$var wire 1 = XM_MemRead $end
$var wire 1 > XM_MemWrite $end
$var wire 1 ? XM_MemtoReg $end
$var wire 5 s XM_RD [4:0] $end
$var wire 1 A XM_RegWrite $end
$var wire 1 C clk $end
$var wire 1 E rst $end
$var reg 32 t MDR [31:0] $end
$var reg 32 u MW_ALUout [31:0] $end
$var reg 1 v MW_MemtoReg $end
$var reg 5 w MW_RD [4:0] $end
$var reg 1 x MW_RegWrite $end
$upscope $end
$upscope $end
$upscope $end
$enddefinitions $end
#0
$dumpvars
0x
b0 w
0v
b0 u
b0 t
b0 s
b0 r
b0 q
0p
0o
b0 n
0m
0l
0k
b0 j
b0 i
b0 h
b0 g
b0 f
bz e
zd
b0 c
bz b
b0 a
b0 `
b0 _
b0 ^
0]
b0 \
0[
0Z
b0 Y
b0 X
0W
0V
0U
b0 T
b0 S
b0 R
b0 Q
b0 P
b0 O
b0 N
b0 M
b0 L
b0 K
b0 J
b0 I
b0 H
b0 G
b0 F
1E
b0 D
1C
0B
0A
b0 @
0?
0>
0=
b0 <
b0 ;
b0 :
09
b0 8
07
b0 6
b0 5
b0 4
b0 3
02
01
00
b0 /
b0 .
b0 -
0,
0+
0*
b0 )
b0 (
b0 '
b0 &
b0 %
b100000 $
b0 #
1"
1!
$end
#10000
0!
0C
#12000
0"
0E
#20000
1Z
10
b100 I
b100 4
b100 N
b1000100001100000100000 H
b1000100001100000100000 3
b1000100001100000100000 J
b1 #
1!
1C
#30000
0!
0C
#40000
b100000 H
b100000 3
b100000 J
b1000 I
b1000 4
b1000 N
b100010000110000010000000 S
b100010000110000010000000 (
b100010000110000010000000 G
b100 X
b100 -
b100 f
b100 R
b100 .
b1100000100000 \
b1100000100000 D
b1100000100000 g
b10 T
b10 )
b10 a
b1 O
b1 %
b1 ^
b11 Y
b11 /
b11 c
b10 Q
b10 '
b10 `
1o
1A
b10 #
1!
1C
#50000
0!
0C
#60000
1x
19
b11 h
b11 :
b11 q
b110000010000100 i
b110000010000100 ;
b110000010000100 F
b10 j
b10 <
b10 r
b11 n
b11 @
b11 s
b0 Y
b0 /
b0 c
b0 Q
b0 '
b0 `
b10000000 S
b10000000 (
b10000000 G
b1000 X
b1000 -
b1000 f
b1000 R
b1000 .
b100000 \
b100000 D
b100000 g
b0 T
b0 )
b0 a
b0 O
b0 %
b0 ^
b1100 I
b1100 4
b1100 N
b11 #
1!
1C
#70000
0!
0C
#80000
b10000 I
b10000 4
b10000 N
b1100 X
b1100 -
b1100 f
b1100 R
b1100 .
b10001000 i
b10001000 ;
b10001000 F
b0 j
b0 <
b0 r
b0 n
b0 @
b0 s
b0 h
b0 :
b0 q
b11 w
b11 8
b11 M
b11 u
b11 6
b11 L
b100 #
1!
1C
#90000
0!
0C
#100000
b0 w
b0 8
b0 M
b0 u
b0 6
b0 L
b10001100 i
b10001100 ;
b10001100 F
b10000 X
b10000 -
b10000 f
b10000 R
b10000 .
b10100 I
b10100 4
b10100 N
bx H
bx 3
bx J
b101 #
1!
1C
#110000
0!
0C
#120000
b11000 I
b11000 4
b11000 N
b0xxxxxxxxxxxxxxxxxxxxxxxxxxx00 S
b0xxxxxxxxxxxxxxxxxxxxxxxxxxx00 (
b0xxxxxxxxxxxxxxxxxxxxxxxxxxx00 G
x]
x2
b10100 X
b10100 -
b10100 f
b10100 R
b10100 .
bx \
bx D
bx g
bx T
bx )
bx a
bx O
bx %
bx ^
b10010000 i
b10010000 ;
b10010000 F
b110 #
1!
1C
#130000
0!
0C
#140000
bx h
bx :
bx q
bx i
bx ;
bx F
bx j
bx <
bx r
b11000 X
b11000 -
b11000 f
b11000 R
b11000 .
b0xxxxxxxxxxxxxxxxxxxxxxxxxxx00 I
b0xxxxxxxxxxxxxxxxxxxxxxxxxxx00 4
b0xxxxxxxxxxxxxxxxxxxxxxxxxxx00 N
b111 #
1!
1C
#150000
0!
0C
#160000
bx I
bx 4
bx N
b0xxxxxxxxxxxxxxxxxxxxxxxxxxxx00 S
b0xxxxxxxxxxxxxxxxxxxxxxxxxxxx00 (
b0xxxxxxxxxxxxxxxxxxxxxxxxxxxx00 G
b0xxxxxxxxxxxxxxxxxxxxxxxxxxx00 X
b0xxxxxxxxxxxxxxxxxxxxxxxxxxx00 -
b0xxxxxxxxxxxxxxxxxxxxxxxxxxx00 f
b0xxxxxxxxxxxxxxxxxxxxxxxxxxx00 R
b0xxxxxxxxxxxxxxxxxxxxxxxxxxx00 .
bx u
bx 6
bx L
b1000 #
1!
1C
#170000
0!
0C
#180000
bx00 S
bx00 (
bx00 G
bx X
bx -
bx f
bx R
bx .
b1001 #
1!
1C
#190000
0!
0C
#200000
b1010 #
1!
1C
#210000
0!
0C
#220000
b1011 #
1!
1C
#230000
0!
0C
#240000
b1100 #
1!
1C
#250000
0!
0C
#260000
b1101 #
1!
1C
#270000
0!
0C
#280000
b1110 #
1!
1C
#290000
0!
0C
#300000
b1111 #
1!
1C
#310000
0!
0C
#320000
b10000 #
1!
1C
#330000
0!
0C
#340000
b10001 #
1!
1C
#350000
0!
0C
#360000
b10010 #
1!
1C
#370000
0!
0C
#380000
b10011 #
1!
1C
#390000
0!
0C
#400000
b10100 #
1!
1C
#410000
0!
0C
#420000
b10101 #
1!
1C
